LICENSE.txt
MANIFEST.in
README.md
requirements.txt
requirements_full.txt
setup.cfg
setup.py
src/Hydro.egg-info/PKG-INFO
src/Hydro.egg-info/SOURCES.txt
src/Hydro.egg-info/dependency_links.txt
src/Hydro.egg-info/entry_points.txt
src/Hydro.egg-info/requires.txt
src/Hydro.egg-info/top_level.txt
src/hydro/__init__.py
src/hydro/base_classes.py
src/hydro/connector_factory.py
src/hydro/exceptions.py
src/hydro/hydro_cli.py
src/hydro/hydro_cluster.py
src/hydro/query_engine.py
src/hydro/query_engine_factory.py
src/hydro/stats_engine.py
src/hydro/topology_base.py
src/hydro/transformers.py
src/hydro/types.py
src/hydro/cache/__init__.py
src/hydro/cache/base_classes.py
src/hydro/cache/in_memory.py
src/hydro/cache/mysql_cache.py
src/hydro/common/__init__.py
src/hydro/common/configurator.py
src/hydro/common/execution_plan.py
src/hydro/common/logger.py
src/hydro/common/utils.py
src/hydro/conf/__init__.py
src/hydro/conf/logger.py
src/hydro/conf/settings.py
src/hydro/conf/settings_base.py
src/hydro/conf/settings_dev.py
src/hydro/connectors/__init__.py
src/hydro/connectors/base_classes.py
src/hydro/connectors/mysql.py
src/hydro/connectors/static.py
src/hydro/connectors/vertica.py
src/hydro/templates/conf.template
src/hydro/templates/optimizer.template
src/hydro/templates/sample.template
src/hydro/templates/topology1.template
src/sample/complex_plan/__init__.py
src/sample/complex_plan/conf.py
src/sample/complex_plan/optimizer.py
src/sample/complex_plan/sample_topology.py
src/sample/geo_queries/__init__.py
src/sample/geo_queries/conf.py
src/sample/geo_queries/geo_widget_topology.py
src/sample/geo_queries/optimizer.py
src/sample/topology_injection/__init__.py
src/sample/topology_injection/conf.py
src/sample/topology_injection/optimizer.py
src/sample/topology_injection/topology_injection_topology.py
src/test/hydro/__init__.py
src/test/hydro/test_base_classes.py
src/test/hydro/test_transformers.py
src/test/hydro/cache/__init__.py
src/test/hydro/cache/test_in_memory.py
src/test/hydro/common/__init__.py
src/test/hydro/common/test_execution_plan.py
src/test/hydro/connectors/__init__.py
src/test/hydro/connectors/check_connections.py
src/test/hydro/connectors/test_conncetor_base.py
