Metadata-Version: 1.1
Name: Hydro
Version: 0.1.3
Summary: On-the-fly data manipulation framework
Home-page: https://github.com/Convertro/Hydro
Author: Convertro
Author-email: moshe.basanchig@convertro.com
License: UNKNOWN
Download-URL: https://github.com/Convertro/Hydro/tarball/0.1
Platform: UNKNOWN
